pydantic_ome_ngff/__init__.py
pydantic_ome_ngff/_version.py
pydantic_ome_ngff/base.py
pydantic_ome_ngff/py.typed
pydantic_ome_ngff/utils.py
pydantic_ome_ngff/latest/__init__.py
pydantic_ome_ngff/latest/axis.py
pydantic_ome_ngff/latest/base.py
pydantic_ome_ngff/latest/label.py
pydantic_ome_ngff/latest/multiscale.py
pydantic_ome_ngff/latest/plate.py
pydantic_ome_ngff/latest/transform.py
pydantic_ome_ngff/latest/well.py
pydantic_ome_ngff/v04/__init__.py
pydantic_ome_ngff/v04/axis.py
pydantic_ome_ngff/v04/base.py
pydantic_ome_ngff/v04/label.py
pydantic_ome_ngff/v04/multiscale.py
pydantic_ome_ngff/v04/plate.py
pydantic_ome_ngff/v04/transform.py
pydantic_ome_ngff/v04/utils.py
pydantic_ome_ngff/v04/well.py
pydantic_ome_ngff-0.6.1.dist-info/METADATA
pydantic_ome_ngff-0.6.1.dist-info/WHEEL
pydantic_ome_ngff-0.6.1.dist-info/licenses/LICENSE
pydantic_ome_ngff-0.6.1.dist-info/RECORD
