Metadata-Version: 2.3
Name: pydantic-ome-ngff
Version: 0.6.1
Summary: Pydantic models for the OME-NGFF file format.
Project-URL: Documentation, https://janeliascicomp.github.io/pydantic-ome-ngff
Project-URL: Issues, https://github.com/janeliascicomp/pydantic-ome-ngff/issues
Project-URL: Source, https://github.com/janeliascicomp/pydantic-ome-ngff
Author-email: Davis Vann Benntt <davis.v.bennett@gmail.com>
License-Expression: MIT
License-File: LICENSE
Keywords: ngff,ome-ngff,pydantic,zarr
Classifier: Development Status :: 4 - Beta
Classifier: Programming Language :: Python
Classifier: Programming Language :: Python :: 3.10
Classifier: Programming Language :: Python :: 3.11
Classifier: Programming Language :: Python :: 3.12
Classifier: Programming Language :: Python :: Implementation :: CPython
Requires-Python: >=3.9
Requires-Dist: pydantic-zarr==0.7.0
